scout/__init__.py
scout/__main__.py
scout/client.py
scout/constants.py
scout/exceptions.py
scout/models.py
scout/search.py
scout/serializers.py
scout/server.py
scout/tests.py
scout/validator.py
scout/views.py
scout-3.0.4.dist-info/licenses/LICENSE
scout-3.0.4.dist-info/METADATA
scout-3.0.4.dist-info/WHEEL
scout-3.0.4.dist-info/entry_points.txt
scout-3.0.4.dist-info/top_level.txt
scout-3.0.4.dist-info/RECORD
