Metadata-Version: 2.4
Name: scout
Version: 3.0.4
Summary: a lightweight search server powered by sqlite
Author-email: Charles Leifer <coleifer@gmail.com>
License: Copyright (c) 2014 Charles Leifer
Project-URL: Repository, https://github.com/coleifer/scout
Project-URL: Documentation, https://scout.readthedocs.io/
Classifier: Environment :: Web Environment
Classifier: Programming Language :: Python :: 2
Classifier: Programming Language :: Python :: 3
Classifier: Topic :: Database
Classifier: Topic :: Database :: Front-Ends
Classifier: Topic :: Software Development :: Libraries :: Python Modules
License-File: LICENSE
Requires-Dist: flask
Requires-Dist: peewee>=3.0.0
Dynamic: license-file
